invenio_config_iform/__about__.py
invenio_config_iform/__init__.py
invenio_config_iform/config.py
invenio_config_iform/ext.py
invenio_config_iform/utils.py
invenio_config_iform/views.py
invenio_config_iform/custom_fields/__init__.py
invenio_config_iform/permissions/__init__.py
invenio_config_iform/permissions/generators.py
invenio_config_iform/permissions/policies.py
invenio_config_iform/permissions/roles.py
invenio_config_iform/restrictions/access_right/access_right.csv
invenio_config_iform/restrictions/access_right/access_right_limit.csv
invenio_config_iform/static/documents/TUGraz_Repository_General_Data_Protection_Rights_de.pdf
invenio_config_iform/static/documents/TUGraz_Repository_General_Data_Protection_Rights_en.pdf
invenio_config_iform/static/documents/TUGraz_Repository_Guide_01_de.pdf
invenio_config_iform/static/documents/TUGraz_Repository_Guide_01_en.pdf
invenio_config_iform/static/documents/TUGraz_Repository_Guide_02.1_de.pdf
invenio_config_iform/static/documents/TUGraz_Repository_Guide_02.1_en.pdf
invenio_config_iform/static/documents/TUGraz_Repository_Guide_02_de.pdf
invenio_config_iform/static/documents/TUGraz_Repository_Guide_02_en.pdf
invenio_config_iform/static/documents/TUGraz_Repository_Terms_And_Conditions_de.pdf
invenio_config_iform/static/documents/TUGraz_Repository_Terms_And_Conditions_en.pdf
invenio_config_iform/templates/security/email/welcome.txt
invenio_config_iform/translations/.gitkeep
invenio_config_iform/translations/messages.pot
invenio_config_iform/translations/de/LC_MESSAGES/messages.po
invenio_config_iform-2025.5.20.21.dist-info/METADATA
invenio_config_iform-2025.5.20.21.dist-info/WHEEL
invenio_config_iform-2025.5.20.21.dist-info/entry_points.txt
invenio_config_iform-2025.5.20.21.dist-info/licenses/AUTHORS.rst
invenio_config_iform-2025.5.20.21.dist-info/licenses/LICENSE
invenio_config_iform-2025.5.20.21.dist-info/RECORD
