Metadata-Version: 2.4
Name: invenio-config-iform
Version: 2025.5.20.21
Summary: Invenio module that adds I-Form configs.
Project-URL: Homepage, https://github.com/Cian-H/invenio-config-iform
Project-URL: Issues, https://github.com/Cian-H/invenio-config-iform/issues
Author-email: I-Form Advanced Research Manufacturing Research Centre <cian.hughes@dcu.ie>
License-Expression: MIT
License-File: AUTHORS.rst
License-File: LICENSE
Keywords: I-Form,config,invenio
Classifier: Development Status :: 3 - Alpha
Classifier: Environment :: Web Environment
Classifier: Intended Audience :: Developers
Classifier: Operating System :: OS Independent
Classifier: Programming Language :: Python
Classifier: Programming Language :: Python :: 3.10
Classifier: Programming Language :: Python :: 3.11
Classifier: Programming Language :: Python :: 3.12
Classifier: Programming Language :: Python :: 3.13
Classifier: Topic :: Internet :: WWW/HTTP :: Dynamic Content
Classifier: Topic :: Software Development :: Libraries :: Python Modules
Requires-Python: <3.14,>=3.10
Requires-Dist: invenio-cache>=1.1.1
Requires-Dist: invenio-i18n>=2.0.0
Requires-Dist: invenio-rdm-records>=4.0.0
